README.md
setup.py
cvopt/__init__.py
cvopt.egg-info/PKG-INFO
cvopt.egg-info/SOURCES.txt
cvopt.egg-info/dependency_links.txt
cvopt.egg-info/requires.txt
cvopt.egg-info/top_level.txt
cvopt/model_selection/__init__.py
cvopt/model_selection/_base.py
cvopt/model_selection/_ga.py
cvopt/model_selection/_search.py
cvopt/model_selection/_setting.py
cvopt/search_setting/__init__.py
cvopt/search_setting/_base.py
cvopt/utils/__init__.py
cvopt/utils/_base.py
cvopt/utils/_html.py
cvopt/utils/_htmlsrc.py
cvopt/utils/_logger.py
cvopt/utils/_logoperator.py