Metadata-Version: 1.0
Name: cvopt
Version: 0.4.1
Summary: Parameter search and feature selection's class, Integrated visualization and archive log.
Home-page: https://github.com/genfifth/cvopt.git
Author: gen/5
Author-email: gen_fifth@outlook.jp
License: BSD-2-Clause
Platform: UNKNOWN
